endee_llamaindex/__init__.py
endee_llamaindex/base.py
endee_llamaindex/utils.py
endee_llamaindex-0.1.3.dist-info/METADATA
endee_llamaindex-0.1.3.dist-info/WHEEL
endee_llamaindex-0.1.3.dist-info/top_level.txt
endee_llamaindex-0.1.3.dist-info/RECORD
