Metadata-Version: 2.4
Name: endee-llamaindex
Version: 0.1.3
Summary: Vector Database for Fast ANN Searches
Home-page: https://endee.io
Author: Endee Labs
Author-email: vineet@endee.io
Classifier: Programming Language :: Python :: 3
Classifier: License :: OSI Approved :: MIT License
Classifier: Operating System :: OS Independent
Requires-Python: >=3.6
Requires-Dist: llama-index>=0.12.34
Requires-Dist: endee>=0.1.4
Dynamic: author
Dynamic: author-email
Dynamic: classifier
Dynamic: description
Dynamic: description-content-type
Dynamic: home-page
Dynamic: requires-dist
Dynamic: requires-python
Dynamic: summary
